distribapi/__init__.py
distribapi/core.py
distribapi/version.py
distribapi-1.0.dist-info/licenses/LICENSE
distribapi-1.0.dist-info/METADATA
distribapi-1.0.dist-info/WHEEL
distribapi-1.0.dist-info/top_level.txt
distribapi-1.0.dist-info/RECORD
