Metadata-Version: 2.4
Name: distribapi
Version: 1.0
Summary: Intelligent API request distribution based on system resources and latency
Home-page: https://github.com/QKing-Official/distribapi
Author: QKing
Author-email: QKing <qking@qking.me>
License: MIT
Project-URL: Homepage, https://github.com/QKing-Official/distribapi
Project-URL: Repository, https://github.com/QKing-Official/distribapi
Requires-Python: >=3.8
License-File: LICENSE
Requires-Dist: aiohttp>=3.8.0
Requires-Dist: psutil>=5.9.0
Provides-Extra: gpu
Requires-Dist: gputil>=1.4.0; extra == "gpu"
Provides-Extra: dev
Requires-Dist: pytest>=7.0.0; extra == "dev"
Requires-Dist: pytest-asyncio>=0.21.0; extra == "dev"
Requires-Dist: pytest-cov>=4.0.0; extra == "dev"
Requires-Dist: black>=23.0.0; extra == "dev"
Requires-Dist: flake8>=6.0.0; extra == "dev"
Requires-Dist: mypy>=1.0.0; extra == "dev"
Dynamic: author
Dynamic: home-page
Dynamic: license-file
Dynamic: requires-python
